{"coins": 0.0, "all_time_coins": 0.0, "prestige": 0, "click_upgrades": [{"owned": 0}, {"owned": 0}, {"owned": 0}, {"owned": 0}, {"owned": 0}, {"owned": 0}, {"owned": 0}, {"owned": 0}, {"owned": 0}, {"owned": 0}], "auto_upgrades": [{"owned": 0}, {"owned": 0}, {"owned": 0}, {"owned": 0}, {"owned": 0}, {"owned": 0}, {"owned": 0}, {"owned": 0}, {"owned": 0}, {"owned": 0}, {"owned": 0}, {"owned": 0}, {"owned": 0}, {"owned": 0}, {"owned": 0}, {"owned": 0}, {"owned": 0}, {"owned": 0}, {"owned": 0}, {"owned": 0}], "last_saved_time": 1748541895.0586116, "buy_multiplier_index": 0, "total_clicks": 0, "click_times": [], "start_time": 1748540145.6123254, "prestige_start_time": 1748540145.6123254, "coin_bag_shake_enabled": true, "sound_volume": 5, "achievements": [{"completed": false, "unlocked_time": null}, {"completed": false, "unlocked_time": null}, {"completed": false, "unlocked_time": null}, {"completed": false, "unlocked_time": null}, {"completed": false, "unlocked_time": null}, {"completed": false, "unlocked_time": null}, {"completed": false, "unlocked_time": null}, {"completed": false, "unlocked_time": null}, {"completed": false, "unlocked_time": null}, {"completed": false, "unlocked_time": null}, {"completed": false, "unlocked_time": null}, {"completed": false, "unlocked_time": null}, {"completed": false, "unlocked_time": null}, {"completed": false, "unlocked_time": null}, {"completed": false, "unlocked_time": null}, {"completed": false, "unlocked_time": null}], "achievement_scroll": 0, "has_new_achievement": false, "achievement_unlocked_queue": [], "current_achievement_popup": null, "achievement_popup_time": 0}