{"coins": 15.0, "all_time_coins": 15.0, "prestige": 0, "click_upgrades": [{"owned": 0}, {"owned": 0}, {"owned": 0}, {"owned": 0}, {"owned": 0}, {"owned": 0}, {"owned": 0}, {"owned": 0}, {"owned": 0}, {"owned": 0}], "auto_upgrades": [{"owned": 0}, {"owned": 0}, {"owned": 0}, {"owned": 0}, {"owned": 0}, {"owned": 0}, {"owned": 0}, {"owned": 0}, {"owned": 0}, {"owned": 0}, {"owned": 0}, {"owned": 0}, {"owned": 0}, {"owned": 0}, {"owned": 0}, {"owned": 0}, {"owned": 0}, {"owned": 0}, {"owned": 0}, {"owned": 0}], "last_saved_time": 1748546156.4581647, "buy_multiplier_index": 0, "total_clicks": 15, "click_times": [1748546099.1044242, 1748546099.2131658, 1748546099.37267, 1748546099.698772, 1748546099.8113203, 1748546099.9265835, 1748546100.2723114, 1748546100.3404562, 1748546100.4943101, 1748546100.5191524, 1748546100.617441, 1748546100.7477021, 1748546100.9660485, 1748546101.0810738, 1748546101.15807], "start_time": 1748546097.020414, "prestige_start_time": 1748546097.020414, "coin_bag_shake_enabled": true, "sound_volume": 5, "achievements": [{"completed": true, "unlocked_time": 1748546100.5191524}, {"completed": false, "unlocked_time": null}, {"completed": false, "unlocked_time": null}, {"completed": false, "unlocked_time": null}, {"completed": false, "unlocked_time": null}, {"completed": false, "unlocked_time": null}, {"completed": true, "unlocked_time": 1748546100.5191524}, {"completed": false, "unlocked_time": null}, {"completed": false, "unlocked_time": null}, {"completed": false, "unlocked_time": null}, {"completed": false, "unlocked_time": null}, {"completed": false, "unlocked_time": null}, {"completed": false, "unlocked_time": null}, {"completed": false, "unlocked_time": null}, {"completed": false, "unlocked_time": null}, {"completed": false, "unlocked_time": null}], "achievement_scroll": 0, "has_new_achievement": true, "achievement_unlocked_queue": [], "current_achievement_popup": null, "achievement_popup_time": 0}